auxi/chemistry/__init__.py
auxi/chemistry/py.typed
auxi/chemistry/stoichiometry/__init__.py
auxi/chemistry/stoichiometry/_chemical_formula_parse_result.py
auxi/chemistry/stoichiometry/_chemical_formula_parser.ebnf
auxi/chemistry/stoichiometry/_chemical_formula_parser.py
auxi/chemistry/stoichiometry/_elements.py
auxi/chemistry/stoichiometry/_functions.py
auxi/chemistry/stoichiometry/_stoichiometry_record.py
auxi/chemistry/stoichiometry/py.typed
auxi/chemistry/validation/__init__.py
auxi/chemistry/validation/_chemical_compositions.py
auxi/chemistry/validation/_compound_formulas.py
auxi/chemistry/validation/py.typed
auxi_chemistry-2.7.7.dist-info/licenses/LICENSE.md
auxi_chemistry-2.7.7.dist-info/METADATA
auxi_chemistry-2.7.7.dist-info/WHEEL
auxi_chemistry-2.7.7.dist-info/top_level.txt
auxi_chemistry-2.7.7.dist-info/RECORD
