Metadata-Version: 2.4
Name: auxi-chemistry
Version: 2.7.7
Summary: `auxi` provides tools to help users do calculations for metallurgical process engineering. `auxi-chemistry` provides tools related to chemistry.
Author-email: Johan Zietsman <johan.zietsman@ex-mente.co.za>
Maintainer-email: Stefan van der Merwe <stefan.vandermerwe@ex-mente.co.za>, Thys Nortje <thys.nortje@ex-mente.co.za>
License-Expression: MIT
Project-URL: Repository, https://gitlab.com/auxi-oss/auxi-chemistry.git
Project-URL: Issues, https://gitlab.com/auxi-oss/auxi-chemistry/-/issues
Classifier: Development Status :: 5 - Production/Stable
Classifier: Programming Language :: Python :: 3
Classifier: Operating System :: POSIX :: Linux
Classifier: Environment :: Console
Requires-Python: >=3.12
License-File: LICENSE.md
Requires-Dist: auxi-core>=2.2.1
Requires-Dist: numpy>=2.1.3
Requires-Dist: parsimonious>=0.10.0
Requires-Dist: scipy>=1.14.1
Dynamic: license-file
